MANIFEST.in
pytest.ini
setup.py
docs/HISTORY.txt
src/dolmen/__init__.py
src/dolmen.container.egg-info/PKG-INFO
src/dolmen.container.egg-info/SOURCES.txt
src/dolmen.container.egg-info/dependency_links.txt
src/dolmen.container.egg-info/namespace_packages.txt
src/dolmen.container.egg-info/not-zip-safe
src/dolmen.container.egg-info/requires.txt
src/dolmen.container.egg-info/top_level.txt
src/dolmen/container/README.txt
src/dolmen/container/__init__.py
src/dolmen/container/components.py
src/dolmen/container/interfaces.py
src/dolmen/container/tests/__init__.py
src/dolmen/container/tests/test_btree.py
src/dolmen/container/tests/test_ordered.py