Metadata-Version: 1.0
Name: dolmen.container
Version: 0.2
Summary: Dolmen containers components
Home-page: UNKNOWN
Author: The Dolmen team
Author-email: dolmen@list.dolmen-project.org
License: ZPL
Keywords: Dolmen container implementation,using ZODB BTrees.
Platform: Any
Classifier: Environment :: Web Environment
Classifier: Operating System :: OS Independent
Classifier: Programming Language :: Python
